{
  "installed": {
    "client_id": "1071951272873-l0kk00de3gq1m9ab3a9db06ftoeqg93j.apps.googleusercontent.com",
    "project_id": "clodbot-sheets",
    "auth_uri": "https://accounts.google.com/o/oauth2/auth",
    "token_uri": "https://oauth2.googleapis.com/token",
    "auth_provider_x509_cert_url": "https://www.googleapis.com/oauth2/v1/certs",
    "client_secret": "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",
    "redirect_uris": [
      "http://localhost"
    ]
  }
}

{
  "installed": {
    "client_id": "1071951272873-l0kk00de3gq1m9ab3a9db06ftoeqg93j.apps.googleusercontent.com",
    "project_id": "clodbot-sheets",
    "auth_uri": "https://accounts.google.com/o/oauth2/auth",
    "token_uri": "https://oauth2.googleapis.com/token",
    "auth_provider_x509_cert_url": "https://www.googleapis.com/oauth2/v1/certs",
    "client_secret": "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",
    "redirect_uris": [
      "http://localhost"
    ]
  }
}